local_flight_map/__init__.py
local_flight_map/__main__.py
local_flight_map/api/__init__.py
local_flight_map/api/adsbexchange/__init__.py
local_flight_map/api/adsbexchange/client.py
local_flight_map/api/adsbexchange/config.py
local_flight_map/api/adsbexchange/response.py
local_flight_map/api/adsbexchange/feed/__init__.py
local_flight_map/api/adsbexchange/feed/client.py
local_flight_map/api/adsbexchange/feed/config.py
local_flight_map/api/adsbexchange/feed/response.py
local_flight_map/api/base/__init__.py
local_flight_map/api/base/client.py
local_flight_map/api/base/config.py
local_flight_map/api/base/geography.py
local_flight_map/api/base/middleware.py
local_flight_map/api/base/response.py
local_flight_map/api/hexdb/__init__.py
local_flight_map/api/hexdb/client.py
local_flight_map/api/hexdb/config.py
local_flight_map/api/hexdb/response.py
local_flight_map/api/opensky/__init__.py
local_flight_map/api/opensky/client.py
local_flight_map/api/opensky/config.py
local_flight_map/api/opensky/response.py
local_flight_map/ui/__init__.py
local_flight_map/ui/app/__init__.py
local_flight_map/ui/app/config.py
local_flight_map/ui/app/data.py
local_flight_map/ui/app/interface.js
local_flight_map/ui/app/interface.py
local_flight_map/ui/app/layers.py
local_flight_map/ui/app/middleware.py
local_flight_map/ui/app/static/css/components.css
local_flight_map/ui/app/static/css/main.css
local_flight_map/ui/app/static/css/map.css
local_flight_map/ui/app/static/css/variables.css
local_flight_map/ui/app/static/icons/civil_helicopter.png
local_flight_map/ui/app/static/icons/civil_plane_1.png
local_flight_map/ui/app/static/icons/civil_plane_2.png
local_flight_map/ui/app/static/icons/civil_plane_3.png
local_flight_map/ui/app/static/icons/clouds.png
local_flight_map/ui/app/static/icons/forbidden.png
local_flight_map/ui/app/static/icons/mil_plane_1.png
local_flight_map/ui/app/static/icons/mil_plane_2.png
local_flight_map/ui/app/static/icons/police_helicopter.png
local_flight_map-1.1.9.dist-info/licenses/LICENSE
local_flight_map-1.1.9.dist-info/METADATA
local_flight_map-1.1.9.dist-info/WHEEL
local_flight_map-1.1.9.dist-info/entry_points.txt
local_flight_map-1.1.9.dist-info/top_level.txt
local_flight_map-1.1.9.dist-info/RECORD
