Metadata-Version: 2.4
Name: local-flight-map
Version: 1.1.9
Summary: Open Air Traffic map based on ADS-B Exchange and Open Sky Data.
Author-email: Dawid Ciepiela <71898979+sarumaj@users.noreply.github.com>
License: MIT
Classifier: Programming Language :: Python :: 3.12
Classifier: License :: OSI Approved :: MIT License
Classifier: Operating System :: OS Independent
Requires-Python: >=3.12
License-File: LICENSE
Requires-Dist: aiohttp==3.13.2
Requires-Dist: asyncio==4.0.0
Requires-Dist: async-lru==2.0.5
Requires-Dist: fastapi==0.127.0
Requires-Dist: folium==0.20.0
Requires-Dist: itsdangerous==2.2.0
Requires-Dist: nest-asyncio==1.6.0
Requires-Dist: orjson==3.11.5
Requires-Dist: pydantic==2.12.5
Requires-Dist: pydantic-settings==2.12.0
Requires-Dist: uvicorn==0.40.0
Provides-Extra: test
Requires-Dist: pytest==9.0.2; extra == "test"
Requires-Dist: pytest-asyncio==1.3.0; extra == "test"
Dynamic: license-file
